point_rect/__init__.py
point_rect/point_rect.py
point_rect-2.0.0.dist-info/LICENSE.txt
point_rect-2.0.0.dist-info/METADATA
point_rect-2.0.0.dist-info/RECORD
point_rect-2.0.0.dist-info/WHEEL
point_rect-2.0.0.dist-info/top_level.txt
